[
    {
        "id": 0,
        "name": "以太坊ETH瀏覽器",
        "url": "https://etherscan.io/",
        "image": "./區塊鏈瀏覽器圖/logo-etherscan.svg"
    },
    {
        "id": 1,
        "name": "比特幣BTC瀏覽器",
        "url": "https://www.okx.com/zh-hant/web3/explorer/btc",
        "image": "./區塊鏈瀏覽器圖/logo_bitcoin.svg"
    },
    {
        "id": 2,
        "name": "波場TRON瀏覽器",
        "url": "https://tronscan.org/#/",
        "image": "./區塊鏈瀏覽器圖/logo_tronscan.svg"
    },
    {
        "id": 3,
        "name": "BNB瀏覽器",
        "url": "https://bscscan.com/",
        "image": "./區塊鏈瀏覽器圖/logo-bscscan.svg"
    },
    {
        "id": 4,
        "name": "Polygon瀏覽器",
        "url": "https://polygonscan.com/",
        "image": "./區塊鏈瀏覽器圖/logo-polygonscan.svg"
    },
    {
        "id": 5,
        "name": "Solana瀏覽器",
        "url": "https://solscan.io/",
        "image": "./區塊鏈瀏覽器圖/logo-solscan.png"
    },
    {
        "id": 6,
        "name": "雪崩Avax瀏覽器",
        "url": "https://snowtrace.io/",
        "image": "./區塊鏈瀏覽器圖/logo-snowtrace.png"
    },
    {
        "id": 7,
        "name": "OP瀏覽器",
        "url": "https://bscscan.com/",
        "image": "./區塊鏈瀏覽器圖/logo-opMainnet.svg"
    },
    {
        "id": 8,
        "name": "ARB瀏覽器",
        "url": "https://arbiscan.io/",
        "image": "./區塊鏈瀏覽器圖/logo-arbiscan.svg"
    },
    {
        "id": 9,
        "name": "CRO瀏覽器",
        "url": "https://cronoscan.com/",
        "image": "./區塊鏈瀏覽器圖/logo-cronos.svg"
    },
    {
        "id": 10,
        "name": "ZK瀏覽器",
        "url": "https://zkscan.io/",
        "image": "./區塊鏈瀏覽器圖/logo-zksync.png"
    },
    {
        "id": 11,
        "name": "KLAY瀏覽器",
        "url": "https://klaytnscope.com/",
        "image": "./區塊鏈瀏覽器圖/logo-klaytnscope.png"
    },
    {
        "id": 12,
        "name": "EOS瀏覽器",
        "url": "https://eosflare.io/",
        "image": "./區塊鏈瀏覽器圖/logo-eosflare.png"
    },
    {
        "id": 13,
        "name": "ZETA瀏覽器",
        "url": "https://explorer.zetachain.com/",
        "image": "./區塊鏈瀏覽器圖/logo-zetascan.png"
    },
    {
        "id": 14,
        "name": "MERL瀏覽器",
        "url": "https://scan.merlinchain.io/",
        "image": "./區塊鏈瀏覽器圖/logo-merlin.png"
    },
    {
        "id": 15,
        "name": "BASE瀏覽器",
        "url": "https://base.blockscout.com/",
        "image": "./區塊鏈瀏覽器圖/logo-base.png"
    }
]
